README.md
setup.py
Trello_Project/__init__.py
Trello_Project/trello.py
Trello_Project.egg-info/PKG-INFO
Trello_Project.egg-info/SOURCES.txt
Trello_Project.egg-info/dependency_links.txt
Trello_Project.egg-info/entry_points.txt
Trello_Project.egg-info/not-zip-safe
Trello_Project.egg-info/requires.txt
Trello_Project.egg-info/top_level.txt